{
  "openapi": "3.1.0",
  "jsonSchemaDialect": "https://json-schema.org/draft/2020-12/schema",
  "info": {
    "title": "Wolfram Alpha",
    "version": "1.0.0",
    "description": "Wolfram|Alpha computational knowledge API through PaySponge x402. This bundled spec preserves the live PaySponge payment metadata and enriches the three exposed routes with the documented Wolfram request parameters and response types for short answers, simple images, and full results.",
    "x-agentcash-auth": {
      "mode": "paid"
    }
  },
  "servers": [
    {
      "url": "https://wolframalpha.x402.paysponge.com"
    }
  ],
  "security": [],
  "paths": {
    "/v1/result": {
      "get": {
        "summary": "Get a short textual answer",
        "description": "Return a single short plain-text result for a Wolfram|Alpha query. This route is suited to concise computational answers when a full pod structure is unnecessary.",
        "operationId": "getShortAnswer",
        "externalDocs": {
          "description": "Wolfram|Alpha Short Answers API reference",
          "url": "https://products.wolframalpha.com/short-answers-api/documentation/"
        },
        "parameters": [
          {
            "$ref": "#/components/parameters/ShortInput"
          },
          {
            "$ref": "#/components/parameters/Units"
          },
          {
            "$ref": "#/components/parameters/Timeout"
          }
        ],
        "x-agentcash-auth": {
          "mode": "paid"
        },
        "x-payment-required": true,
        "x-payment-info": {
          "protocols": [
            "x402"
          ],
          "pricingMode": "fixed",
          "price": "$0.01"
        },
        "x402Version": 2,
        "resource": {
          "url": "https://wolframalpha.x402.paysponge.com/v1/result",
          "description": "GET /v1/result",
          "mimeType": "application/json"
        },
        "accepts": [
          {
            "scheme": "exact",
            "network": "eip155:8453",
            "payTo": "0xD73912BA30832328a3db96BeE73ebfaB58b7429f",
            "asset": "usdc",
            "amount": "10000",
            "maxTimeoutSeconds": 300,
            "extra": {}
          },
          {
            "scheme": "exact",
            "network": "eip155:43114",
            "payTo": "0xD73912BA30832328a3db96BeE73ebfaB58b7429f",
            "asset": "usdc",
            "amount": "10000",
            "maxTimeoutSeconds": 300,
            "extra": {}
          },
          {
            "scheme": "exact",
            "network": "solana:5eykt4UsFv8P8NJdTREpY1vzqKqZKvdp",
            "payTo": "9hw9Py9uMGtXRNpABZjifcK1t3suwzjyri9L9QYKg6zZ",
            "asset": "usdc",
            "amount": "10000",
            "maxTimeoutSeconds": 300,
            "extra": {}
          }
        ],
        "extensions": {
          "bazaar": {
            "info": {
              "input": {
                "type": "http",
                "method": "GET",
                "query": {
                  "i": "How far is Los Angeles from New York?",
                  "units": "metric"
                }
              },
              "output": {
                "type": "text",
                "example": "3966 kilometers"
              }
            }
          }
        },
        "responses": {
          "200": {
            "description": "A short textual answer returned directly from Wolfram|Alpha.",
            "content": {
              "text/plain": {
                "schema": {
                  "type": "string"
                },
                "examples": {
                  "distance": {
                    "value": "2464 miles"
                  },
                  "metricDistance": {
                    "value": "3966 kilometers"
                  }
                }
              }
            }
          },
          "400": {
            "description": "The request did not include a valid input parameter.",
            "content": {
              "text/plain": {
                "schema": {
                  "type": "string"
                },
                "example": "Error 1000: Input parameter not present in query"
              }
            }
          },
          "402": {
            "description": "Payment Required",
            "content": {
              "application/json": {
                "schema": {
                  "$ref": "#/components/schemas/X402PaymentRequired"
                },
                "example": {
                  "x402Version": 2,
                  "error": "Payment required",
                  "resource": {
                    "url": "https://wolframalpha.x402.paysponge.com/v1/result",
                    "description": "GET /v1/result",
                    "mimeType": "application/json"
                  },
                  "accepts": [
                    {
                      "scheme": "exact",
                      "network": "eip155:8453",
                      "payTo": "0xD73912BA30832328a3db96BeE73ebfaB58b7429f",
                      "asset": "usdc",
                      "amount": "10000",
                      "maxTimeoutSeconds": 300,
                      "extra": {}
                    },
                    {
                      "scheme": "exact",
                      "network": "eip155:43114",
                      "payTo": "0xD73912BA30832328a3db96BeE73ebfaB58b7429f",
                      "asset": "usdc",
                      "amount": "10000",
                      "maxTimeoutSeconds": 300,
                      "extra": {}
                    },
                    {
                      "scheme": "exact",
                      "network": "solana:5eykt4UsFv8P8NJdTREpY1vzqKqZKvdp",
                      "payTo": "9hw9Py9uMGtXRNpABZjifcK1t3suwzjyri9L9QYKg6zZ",
                      "asset": "usdc",
                      "amount": "10000",
                      "maxTimeoutSeconds": 300,
                      "extra": {}
                    }
                  ]
                }
              }
            }
          },
          "501": {
            "description": "Wolfram|Alpha could not interpret the input or no sufficiently short result was available.",
            "content": {
              "text/plain": {
                "schema": {
                  "type": "string"
                }
              }
            }
          }
        }
      }
    },
    "/v1/simple": {
      "get": {
        "summary": "Get a simple rendered image result",
        "description": "Return a single static Wolfram|Alpha image for the query. This route is built for callers that want a complete rendered answer page as an image instead of structured pods.",
        "operationId": "getSimpleImage",
        "externalDocs": {
          "description": "Wolfram|Alpha Simple API reference",
          "url": "https://products.wolframalpha.com/simple-api/documentation"
        },
        "parameters": [
          {
            "$ref": "#/components/parameters/ShortInput"
          },
          {
            "$ref": "#/components/parameters/Layout"
          },
          {
            "$ref": "#/components/parameters/Background"
          },
          {
            "$ref": "#/components/parameters/Foreground"
          },
          {
            "$ref": "#/components/parameters/FontSize"
          },
          {
            "$ref": "#/components/parameters/Width"
          },
          {
            "$ref": "#/components/parameters/Units"
          },
          {
            "$ref": "#/components/parameters/Timeout"
          }
        ],
        "x-agentcash-auth": {
          "mode": "paid"
        },
        "x-payment-required": true,
        "x-payment-info": {
          "protocols": [
            "x402"
          ],
          "pricingMode": "fixed",
          "price": "$0.01"
        },
        "x402Version": 2,
        "resource": {
          "url": "https://wolframalpha.x402.paysponge.com/v1/simple",
          "description": "GET /v1/simple",
          "mimeType": "application/json"
        },
        "accepts": [
          {
            "scheme": "exact",
            "network": "eip155:8453",
            "payTo": "0xD73912BA30832328a3db96BeE73ebfaB58b7429f",
            "asset": "usdc",
            "amount": "10000",
            "maxTimeoutSeconds": 300,
            "extra": {}
          },
          {
            "scheme": "exact",
            "network": "eip155:43114",
            "payTo": "0xD73912BA30832328a3db96BeE73ebfaB58b7429f",
            "asset": "usdc",
            "amount": "10000",
            "maxTimeoutSeconds": 300,
            "extra": {}
          },
          {
            "scheme": "exact",
            "network": "solana:5eykt4UsFv8P8NJdTREpY1vzqKqZKvdp",
            "payTo": "9hw9Py9uMGtXRNpABZjifcK1t3suwzjyri9L9QYKg6zZ",
            "asset": "usdc",
            "amount": "10000",
            "maxTimeoutSeconds": 300,
            "extra": {}
          }
        ],
        "extensions": {
          "bazaar": {
            "info": {
              "input": {
                "type": "http",
                "method": "GET",
                "query": {
                  "i": "What airplanes are flying overhead?",
                  "layout": "labelbar",
                  "width": 400
                }
              },
              "output": {
                "type": "binary"
              }
            }
          }
        },
        "responses": {
          "200": {
            "description": "A rendered result image. Wolfram documents the Simple API as returning a static image result.",
            "content": {
              "image/gif": {
                "schema": {
                  "type": "string",
                  "format": "binary"
                }
              },
              "image/jpeg": {
                "schema": {
                  "type": "string",
                  "format": "binary"
                }
              },
              "application/octet-stream": {
                "schema": {
                  "type": "string",
                  "format": "binary"
                }
              }
            }
          },
          "400": {
            "description": "The request did not include a valid input parameter.",
            "content": {
              "text/plain": {
                "schema": {
                  "type": "string"
                }
              }
            }
          },
          "402": {
            "description": "Payment Required",
            "content": {
              "application/json": {
                "schema": {
                  "$ref": "#/components/schemas/X402PaymentRequired"
                },
                "example": {
                  "x402Version": 2,
                  "error": "Payment required",
                  "resource": {
                    "url": "https://wolframalpha.x402.paysponge.com/v1/simple",
                    "description": "GET /v1/simple",
                    "mimeType": "application/json"
                  },
                  "accepts": [
                    {
                      "scheme": "exact",
                      "network": "eip155:8453",
                      "payTo": "0xD73912BA30832328a3db96BeE73ebfaB58b7429f",
                      "asset": "usdc",
                      "amount": "10000",
                      "maxTimeoutSeconds": 300,
                      "extra": {}
                    },
                    {
                      "scheme": "exact",
                      "network": "eip155:43114",
                      "payTo": "0xD73912BA30832328a3db96BeE73ebfaB58b7429f",
                      "asset": "usdc",
                      "amount": "10000",
                      "maxTimeoutSeconds": 300,
                      "extra": {}
                    },
                    {
                      "scheme": "exact",
                      "network": "solana:5eykt4UsFv8P8NJdTREpY1vzqKqZKvdp",
                      "payTo": "9hw9Py9uMGtXRNpABZjifcK1t3suwzjyri9L9QYKg6zZ",
                      "asset": "usdc",
                      "amount": "10000",
                      "maxTimeoutSeconds": 300,
                      "extra": {}
                    }
                  ]
                }
              }
            }
          },
          "501": {
            "description": "Wolfram|Alpha could not interpret the input or did not cover the topic.",
            "content": {
              "text/plain": {
                "schema": {
                  "type": "string"
                }
              }
            }
          }
        }
      }
    },
    "/v2/query": {
      "get": {
        "summary": "Get full structured Wolfram|Alpha results",
        "description": "Return the full Wolfram|Alpha result structure for a query. By default the upstream API returns XML, and `output=json` switches the response to JSON. This route also supports pod selection, pod states, location hints, timeout controls, and formula-oriented assumptions used by the Instant Calculators workflow.",
        "operationId": "getFullResults",
        "externalDocs": {
          "description": "Wolfram|Alpha Full Results API reference",
          "url": "https://products.wolframalpha.com/api/documentation"
        },
        "parameters": [
          {
            "$ref": "#/components/parameters/FullInput"
          },
          {
            "$ref": "#/components/parameters/Output"
          },
          {
            "$ref": "#/components/parameters/Format"
          },
          {
            "$ref": "#/components/parameters/Assumption"
          },
          {
            "$ref": "#/components/parameters/PodState"
          },
          {
            "$ref": "#/components/parameters/IncludePodId"
          },
          {
            "$ref": "#/components/parameters/ExcludePodId"
          },
          {
            "$ref": "#/components/parameters/PodTitle"
          },
          {
            "$ref": "#/components/parameters/PodIndex"
          },
          {
            "$ref": "#/components/parameters/Scanner"
          },
          {
            "$ref": "#/components/parameters/Location"
          },
          {
            "$ref": "#/components/parameters/LatLong"
          },
          {
            "$ref": "#/components/parameters/Ip"
          },
          {
            "$ref": "#/components/parameters/Width"
          },
          {
            "$ref": "#/components/parameters/MaxWidth"
          },
          {
            "$ref": "#/components/parameters/PlotWidth"
          },
          {
            "$ref": "#/components/parameters/Magnification"
          },
          {
            "$ref": "#/components/parameters/ScanTimeout"
          },
          {
            "$ref": "#/components/parameters/PodTimeout"
          },
          {
            "$ref": "#/components/parameters/FormatTimeout"
          }
        ],
        "x-agentcash-auth": {
          "mode": "paid"
        },
        "x-payment-required": true,
        "x-payment-info": {
          "protocols": [
            "x402"
          ],
          "pricingMode": "fixed",
          "price": "$0.02"
        },
        "x402Version": 2,
        "resource": {
          "url": "https://wolframalpha.x402.paysponge.com/v2/query",
          "description": "GET /v2/query",
          "mimeType": "application/json"
        },
        "accepts": [
          {
            "scheme": "exact",
            "network": "eip155:8453",
            "payTo": "0xD73912BA30832328a3db96BeE73ebfaB58b7429f",
            "asset": "usdc",
            "amount": "20000",
            "maxTimeoutSeconds": 300,
            "extra": {}
          },
          {
            "scheme": "exact",
            "network": "eip155:43114",
            "payTo": "0xD73912BA30832328a3db96BeE73ebfaB58b7429f",
            "asset": "usdc",
            "amount": "20000",
            "maxTimeoutSeconds": 300,
            "extra": {}
          },
          {
            "scheme": "exact",
            "network": "solana:5eykt4UsFv8P8NJdTREpY1vzqKqZKvdp",
            "payTo": "9hw9Py9uMGtXRNpABZjifcK1t3suwzjyri9L9QYKg6zZ",
            "asset": "usdc",
            "amount": "20000",
            "maxTimeoutSeconds": 300,
            "extra": {}
          }
        ],
        "extensions": {
          "bazaar": {
            "info": {
              "input": {
                "type": "http",
                "method": "GET",
                "query": {
                  "input": "pi",
                  "output": "json",
                  "podstate": [
                    "2@DecimalApproximation__More digits"
                  ]
                }
              },
              "output": {
                "type": "json",
                "example": {
                  "queryresult": {
                    "success": true,
                    "error": false,
                    "numpods": 1
                  }
                }
              }
            }
          }
        },
        "responses": {
          "200": {
            "description": "Full Wolfram|Alpha result. XML is the default documented response format; `output=json` switches to JSON.",
            "content": {
              "application/json": {
                "schema": {
                  "$ref": "#/components/schemas/QueryResponse"
                },
                "examples": {
                  "jsonOutput": {
                    "value": {
                      "queryresult": {
                        "success": true,
                        "error": false,
                        "numpods": 2,
                        "datatypes": "Tide",
                        "timedout": "",
                        "timedoutpods": "",
                        "timing": 2.041,
                        "parsetiming": 0.159,
                        "parsetimedout": false,
                        "recalculate": "",
                        "id": "MSPa2841c605802big7c5h700001bi6h0g908bch9ei",
                        "host": "http://www1.wolframalpha.com",
                        "server": "13",
                        "version": "2.6",
                        "pods": [
                          {
                            "title": "Input interpretation",
                            "scanner": "Identity",
                            "id": "Input",
                            "position": 100,
                            "error": false,
                            "numsubpods": 1,
                            "subpods": [
                              {
                                "title": "",
                                "plaintext": "tides Seattle"
                              }
                            ]
                          },
                          {
                            "title": "Result",
                            "scanner": "Tide",
                            "id": "Result",
                            "position": 200,
                            "error": false,
                            "numsubpods": 1,
                            "primary": true,
                            "subpods": [
                              {
                                "title": "",
                                "plaintext": "Tuesday, February 11, 2014 | high tide | 4:06 am PST | +11 feet",
                                "img": {
                                  "src": "http://www1.wolframalpha.com/Calculate/MSP/MSP2871c605802big7c5h70000185h5d64e91gb027?MSPStoreType=image/gif&s=13",
                                  "alt": "Tuesday, February 11, 2014 | high tide | 4:06 am PST | +11 feet",
                                  "width": 400,
                                  "height": 326
                                }
                              }
                            ]
                          }
                        ]
                      }
                    }
                  }
                }
              },
              "application/xml": {
                "schema": {
                  "type": "string"
                },
                "example": "<queryresult success=\"true\" error=\"false\" numpods=\"4\" datatypes=\"Tide\" timedout=\"\" timedoutpods=\"\" timing=\"2.041\" parsetiming=\"0.159\" parsetimedout=\"false\" recalculate=\"\" id=\"MSPa2841c605802big7c5h700001bi6h0g908bch9ei\" host=\"http://www1.wolframalpha.com\" server=\"13\" version=\"2.6\"><pod title=\"Input interpretation\" scanner=\"Identity\" id=\"Input\" position=\"100\" error=\"false\" numsubpods=\"1\">...</pod><pod title=\"Result\" scanner=\"Tide\" id=\"Result\" position=\"200\" error=\"false\" numsubpods=\"1\" primary=\"true\">...</pod></queryresult>"
              },
              "text/xml": {
                "schema": {
                  "type": "string"
                }
              }
            }
          },
          "400": {
            "description": "The request did not include a valid input parameter.",
            "content": {
              "text/plain": {
                "schema": {
                  "type": "string"
                },
                "example": "Error 1000: Input parameter not present in query"
              }
            }
          },
          "402": {
            "description": "Payment Required",
            "content": {
              "application/json": {
                "schema": {
                  "$ref": "#/components/schemas/X402PaymentRequired"
                },
                "example": {
                  "x402Version": 2,
                  "error": "Payment required",
                  "resource": {
                    "url": "https://wolframalpha.x402.paysponge.com/v2/query",
                    "description": "GET /v2/query",
                    "mimeType": "application/json"
                  },
                  "accepts": [
                    {
                      "scheme": "exact",
                      "network": "eip155:8453",
                      "payTo": "0xD73912BA30832328a3db96BeE73ebfaB58b7429f",
                      "asset": "usdc",
                      "amount": "20000",
                      "maxTimeoutSeconds": 300,
                      "extra": {}
                    },
                    {
                      "scheme": "exact",
                      "network": "eip155:43114",
                      "payTo": "0xD73912BA30832328a3db96BeE73ebfaB58b7429f",
                      "asset": "usdc",
                      "amount": "20000",
                      "maxTimeoutSeconds": 300,
                      "extra": {}
                    },
                    {
                      "scheme": "exact",
                      "network": "solana:5eykt4UsFv8P8NJdTREpY1vzqKqZKvdp",
                      "payTo": "9hw9Py9uMGtXRNpABZjifcK1t3suwzjyri9L9QYKg6zZ",
                      "asset": "usdc",
                      "amount": "20000",
                      "maxTimeoutSeconds": 300,
                      "extra": {}
                    }
                  ]
                }
              }
            }
          }
        }
      }
    }
  },
  "x402Version": 2,
  "resource": {
    "url": "https://wolframalpha.x402.paysponge.com/",
    "description": "Wolfram|Alpha computational knowledge API — full results, short answers, simple (image), spoken, and conversational endpoints backed by the Wolfram|Alpha computational engine.",
    "mimeType": "application/json"
  },
  "accepts": [
    {
      "scheme": "exact",
      "network": "eip155:8453",
      "payTo": "0xD73912BA30832328a3db96BeE73ebfaB58b7429f",
      "asset": "usdc",
      "amount": "10000",
      "maxTimeoutSeconds": 300,
      "extra": {}
    },
    {
      "scheme": "exact",
      "network": "eip155:43114",
      "payTo": "0xD73912BA30832328a3db96BeE73ebfaB58b7429f",
      "asset": "usdc",
      "amount": "10000",
      "maxTimeoutSeconds": 300,
      "extra": {}
    },
    {
      "scheme": "exact",
      "network": "solana:5eykt4UsFv8P8NJdTREpY1vzqKqZKvdp",
      "payTo": "9hw9Py9uMGtXRNpABZjifcK1t3suwzjyri9L9QYKg6zZ",
      "asset": "usdc",
      "amount": "10000",
      "maxTimeoutSeconds": 300,
      "extra": {}
    }
  ],
  "x-payment-accepts": [
    {
      "scheme": "exact",
      "network": "eip155:8453",
      "payTo": "0xD73912BA30832328a3db96BeE73ebfaB58b7429f"
    },
    {
      "scheme": "exact",
      "network": "eip155:43114",
      "payTo": "0xD73912BA30832328a3db96BeE73ebfaB58b7429f"
    },
    {
      "scheme": "exact",
      "network": "solana:5eykt4UsFv8P8NJdTREpY1vzqKqZKvdp",
      "payTo": "9hw9Py9uMGtXRNpABZjifcK1t3suwzjyri9L9QYKg6zZ"
    }
  ],
  "components": {
    "parameters": {
      "ShortInput": {
        "name": "i",
        "in": "query",
        "required": true,
        "description": "The natural-language Wolfram|Alpha query input. The short-answer and simple-image APIs document this parameter name as `i`.",
        "schema": {
          "type": "string",
          "minLength": 1
        },
        "example": "How far is Los Angeles from New York?"
      },
      "Units": {
        "name": "units",
        "in": "query",
        "required": false,
        "description": "Select the unit system for measurements and quantities.",
        "schema": {
          "type": "string",
          "enum": [
            "metric",
            "imperial"
          ]
        }
      },
      "Timeout": {
        "name": "timeout",
        "in": "query",
        "required": false,
        "description": "Maximum processing time in seconds. Wolfram documents a default of 5 seconds for the short-answer and simple-image APIs.",
        "schema": {
          "type": "number",
          "minimum": 0
        },
        "example": 5
      },
      "Layout": {
        "name": "layout",
        "in": "query",
        "required": false,
        "description": "Presentation style for simple-image output.",
        "schema": {
          "type": "string",
          "enum": [
            "divider",
            "labelbar"
          ]
        }
      },
      "Background": {
        "name": "background",
        "in": "query",
        "required": false,
        "description": "Background color for the rendered simple-image output. Wolfram documents HTML color names, hexadecimal RGB values, comma-separated RGB values, RGBA-like values with alpha, and `transparent` or `clear`.",
        "schema": {
          "type": "string"
        },
        "example": "F5F5F5"
      },
      "Foreground": {
        "name": "foreground",
        "in": "query",
        "required": false,
        "description": "Foreground text color for simple-image output.",
        "schema": {
          "type": "string",
          "enum": [
            "black",
            "white"
          ]
        }
      },
      "FontSize": {
        "name": "fontsize",
        "in": "query",
        "required": false,
        "description": "Display size of text elements in points. Wolfram documents a default of 14.",
        "schema": {
          "type": "integer",
          "minimum": 1
        },
        "example": 16
      },
      "Width": {
        "name": "width",
        "in": "query",
        "required": false,
        "description": "Desired width in pixels. Wolfram documents a default of 500 for the Simple API and uses width controls for image-oriented Full Results formats as well.",
        "schema": {
          "type": "integer",
          "minimum": 1
        },
        "example": 400
      },
      "FullInput": {
        "name": "input",
        "in": "query",
        "required": true,
        "description": "The natural-language Wolfram|Alpha query input for the Full Results API.",
        "schema": {
          "type": "string",
          "minLength": 1
        },
        "example": "population of france"
      },
      "Output": {
        "name": "output",
        "in": "query",
        "required": false,
        "description": "Switch the documented Full Results response from its default XML shape to JSON. Wolfram documents `output=json`; omitting the parameter returns XML.",
        "schema": {
          "type": "string"
        },
        "example": "json"
      },
      "Format": {
        "name": "format",
        "in": "query",
        "required": false,
        "description": "Comma-separated list of pod output formats to include. The Full Results docs explicitly describe `image`, `imagemap`, `plaintext`, `mathml`, `minput`, `moutput`, and `cell`.",
        "style": "form",
        "explode": false,
        "schema": {
          "type": "array",
          "items": {
            "type": "string",
            "enum": [
              "image",
              "imagemap",
              "plaintext",
              "mathml",
              "minput",
              "moutput",
              "cell"
            ]
          }
        },
        "example": [
          "plaintext",
          "image"
        ]
      },
      "Assumption": {
        "name": "assumption",
        "in": "query",
        "required": false,
        "description": "One or more Wolfram assumption directives. This includes ordinary interpretation assumptions from Full Results and the formula-oriented assumption forms documented by the Instant Calculators API, such as `FSelect_**RAIDArray-`, `*FP.RAIDArray.RAIDLevel-_RAID6`, `*F.RAIDArray.disks-_4`, `*FS-_**RAIDArray.size--`, and `*FVarOpt-_**RAIDArray.spareDisks--`.",
        "style": "form",
        "explode": true,
        "schema": {
          "type": "array",
          "items": {
            "type": "string"
          }
        }
      },
      "PodState": {
        "name": "podstate",
        "in": "query",
        "required": false,
        "description": "One or more pod-state changes from the `input` attribute of a `<state>` element, used for drilldown and alternate pod views. Wolfram also documents the multiplicity shortcut form such as `2@DecimalApproximation__More digits`.",
        "style": "form",
        "explode": true,
        "schema": {
          "type": "array",
          "items": {
            "type": "string"
          }
        },
        "example": [
          "DecimalApproximation__More digits"
        ]
      },
      "IncludePodId": {
        "name": "includepodid",
        "in": "query",
        "required": false,
        "description": "Pod IDs to include in the result. Use repeated parameters for multiple values.",
        "style": "form",
        "explode": true,
        "schema": {
          "type": "array",
          "items": {
            "type": "string"
          }
        }
      },
      "ExcludePodId": {
        "name": "excludepodid",
        "in": "query",
        "required": false,
        "description": "Pod IDs to exclude from the result. Use repeated parameters for multiple values.",
        "style": "form",
        "explode": true,
        "schema": {
          "type": "array",
          "items": {
            "type": "string"
          }
        }
      },
      "PodTitle": {
        "name": "podtitle",
        "in": "query",
        "required": false,
        "description": "Pod titles to include in the result. Wolfram documents `*` wildcard matching and repeated parameters for multiple values.",
        "style": "form",
        "explode": true,
        "schema": {
          "type": "array",
          "items": {
            "type": "string"
          }
        }
      },
      "PodIndex": {
        "name": "podindex",
        "in": "query",
        "required": false,
        "description": "Comma-separated pod indices to return.",
        "style": "form",
        "explode": false,
        "schema": {
          "type": "array",
          "items": {
            "type": "integer",
            "minimum": 1
          }
        },
        "example": [
          1,
          2,
          4
        ]
      },
      "Scanner": {
        "name": "scanner",
        "in": "query",
        "required": false,
        "description": "One or more scanner names to include. Wolfram documents both comma-separated and repeated forms.",
        "style": "form",
        "explode": true,
        "schema": {
          "type": "array",
          "items": {
            "type": "string"
          }
        },
        "example": [
          "Numeric",
          "MathematicalFunctionData"
        ]
      },
      "Location": {
        "name": "location",
        "in": "query",
        "required": false,
        "description": "Location string used to guide geospatial interpretation and local defaults.",
        "schema": {
          "type": "string"
        },
        "example": "Champaign, Illinois"
      },
      "LatLong": {
        "name": "latlong",
        "in": "query",
        "required": false,
        "description": "Latitude and longitude hint used to determine a location.",
        "schema": {
          "type": "string"
        },
        "example": "40.1164,-88.2434"
      },
      "Ip": {
        "name": "ip",
        "in": "query",
        "required": false,
        "description": "Caller IP address to determine location. Wolfram documents this for forwarded end-user requests.",
        "schema": {
          "type": "string"
        },
        "example": "203.0.113.42"
      },
      "MaxWidth": {
        "name": "maxwidth",
        "in": "query",
        "required": false,
        "description": "Maximum width to use for returned pod images or cell renderings.",
        "schema": {
          "type": "integer",
          "minimum": 1
        }
      },
      "PlotWidth": {
        "name": "plotwidth",
        "in": "query",
        "required": false,
        "description": "Requested plot width for graphical results.",
        "schema": {
          "type": "integer",
          "minimum": 1
        }
      },
      "Magnification": {
        "name": "mag",
        "in": "query",
        "required": false,
        "description": "Image magnification factor for certain rendered outputs.",
        "schema": {
          "type": "number",
          "minimum": 0
        }
      },
      "ScanTimeout": {
        "name": "scantimeout",
        "in": "query",
        "required": false,
        "description": "Maximum time in seconds for the scan stage. Wolfram documents a default of 3 seconds.",
        "schema": {
          "type": "number",
          "minimum": 0
        },
        "example": 1
      },
      "PodTimeout": {
        "name": "podtimeout",
        "in": "query",
        "required": false,
        "description": "Maximum time in seconds for formatting any one pod before it is dropped from the output.",
        "schema": {
          "type": "number",
          "minimum": 0
        },
        "example": 0.3
      },
      "FormatTimeout": {
        "name": "formattimeout",
        "in": "query",
        "required": false,
        "description": "Maximum time in seconds for the entire format stage.",
        "schema": {
          "type": "number",
          "minimum": 0
        }
      }
    },
    "schemas": {
      "QueryResponse": {
        "type": "object",
        "properties": {
          "queryresult": {
            "$ref": "#/components/schemas/QueryResult"
          }
        },
        "required": [
          "queryresult"
        ],
        "additionalProperties": true
      },
      "QueryResult": {
        "type": "object",
        "properties": {
          "success": {
            "type": "boolean"
          },
          "error": {
            "type": "boolean"
          },
          "numpods": {
            "type": "integer"
          },
          "datatypes": {
            "type": "string"
          },
          "timedout": {
            "type": "string"
          },
          "timedoutpods": {
            "type": "string"
          },
          "timing": {
            "type": "number"
          },
          "parsetiming": {
            "type": "number"
          },
          "parsetimedout": {
            "type": "boolean"
          },
          "recalculate": {
            "type": "string"
          },
          "id": {
            "type": "string"
          },
          "host": {
            "type": "string"
          },
          "server": {
            "type": "string"
          },
          "version": {
            "type": "string"
          },
          "pods": {
            "type": "array",
            "items": {
              "$ref": "#/components/schemas/Pod"
            }
          },
          "assumptions": {
            "type": "object",
            "additionalProperties": true
          },
          "warnings": {
            "type": "object",
            "additionalProperties": true
          },
          "sources": {
            "type": "object",
            "additionalProperties": true
          }
        },
        "required": [
          "success",
          "error"
        ],
        "additionalProperties": true
      },
      "Pod": {
        "type": "object",
        "properties": {
          "title": {
            "type": "string"
          },
          "scanner": {
            "type": "string"
          },
          "id": {
            "type": "string"
          },
          "position": {
            "type": "integer"
          },
          "error": {
            "type": "boolean"
          },
          "numsubpods": {
            "type": "integer"
          },
          "primary": {
            "type": "boolean"
          },
          "subpods": {
            "type": "array",
            "items": {
              "$ref": "#/components/schemas/Subpod"
            }
          },
          "states": {
            "type": "object",
            "additionalProperties": true
          },
          "infos": {
            "type": "object",
            "additionalProperties": true
          }
        },
        "additionalProperties": true
      },
      "Subpod": {
        "type": "object",
        "properties": {
          "title": {
            "type": "string"
          },
          "plaintext": {
            "type": "string"
          },
          "img": {
            "$ref": "#/components/schemas/WolframImage"
          },
          "mathml": {
            "type": "string"
          },
          "minput": {
            "type": "string"
          },
          "moutput": {
            "type": "string"
          },
          "cell": {
            "type": "string"
          },
          "states": {
            "type": "object",
            "additionalProperties": true
          }
        },
        "additionalProperties": true
      },
      "WolframImage": {
        "type": "object",
        "properties": {
          "src": {
            "type": "string"
          },
          "alt": {
            "type": "string"
          },
          "title": {
            "type": "string"
          },
          "width": {
            "type": "integer"
          },
          "height": {
            "type": "integer"
          }
        },
        "additionalProperties": true
      },
      "X402PaymentRequired": {
        "type": "object",
        "properties": {
          "x402Version": {
            "type": "integer",
            "const": 2
          },
          "error": {
            "type": "string"
          },
          "resource": {
            "$ref": "#/components/schemas/X402Resource"
          },
          "accepts": {
            "type": "array",
            "items": {
              "$ref": "#/components/schemas/X402Accept"
            },
            "minItems": 1
          },
          "extensions": {
            "type": "object",
            "additionalProperties": true
          }
        },
        "required": [
          "x402Version",
          "resource",
          "accepts"
        ],
        "additionalProperties": true
      },
      "X402Resource": {
        "type": "object",
        "properties": {
          "url": {
            "type": "string"
          },
          "description": {
            "type": "string"
          },
          "mimeType": {
            "type": "string"
          }
        },
        "required": [
          "url",
          "description",
          "mimeType"
        ],
        "additionalProperties": false
      },
      "X402Accept": {
        "type": "object",
        "properties": {
          "scheme": {
            "type": "string",
            "const": "exact"
          },
          "network": {
            "type": "string"
          },
          "amount": {
            "type": "string"
          },
          "asset": {
            "type": "string"
          },
          "payTo": {
            "type": "string"
          },
          "maxTimeoutSeconds": {
            "type": "integer"
          },
          "extra": {
            "type": "object",
            "additionalProperties": true
          }
        },
        "required": [
          "scheme",
          "network",
          "amount",
          "asset",
          "payTo",
          "maxTimeoutSeconds",
          "extra"
        ],
        "additionalProperties": false
      }
    }
  }
}
